antimicrobial/__init__.py
antimicrobial-0.1.dist-info/METADATA
antimicrobial-0.1.dist-info/WHEEL
antimicrobial-0.1.dist-info/entry_points.txt
antimicrobial-0.1.dist-info/license_files/LICENSE.txt
antimicrobial-0.1.dist-info/RECORD
