Metadata-Version: 2.1
Name: antimicrobial
Version: 0.1
Summary: Computation tool for antimicrobial agent designing in python
Project-URL: Bug Tracker, https://github.com/JinZhangLab/antimicrobial/issues
Project-URL: Homepage, https://github.com/JinZhangLab/antimicrobial
Author-email: Jin Zhang <jinzhang@nankai.edu.cn>
Classifier: License :: OSI Approved :: MIT License
Classifier: Operating System :: OS Independent
Classifier: Programming Language :: Python :: 3
Requires-Python: >=3.7
